mcp_stargazing-0.1.7.dist-info/licenses/LICENSE
src/__init__.py
src/cache.py
src/celestial.py
src/main.py
src/placefinder.py
src/qweather_interaction.py
src/response.py
src/server_instance.py
src/utils.py
src/functions/__init__.py
src/functions/celestial/__init__.py
src/functions/celestial/impl.py
src/functions/places/__init__.py
src/functions/places/impl.py
src/functions/time/__init__.py
src/functions/time/impl.py
src/functions/weather/__init__.py
src/functions/weather/impl.py
mcp_stargazing-0.1.7.dist-info/METADATA
mcp_stargazing-0.1.7.dist-info/WHEEL
mcp_stargazing-0.1.7.dist-info/entry_points.txt
mcp_stargazing-0.1.7.dist-info/top_level.txt
mcp_stargazing-0.1.7.dist-info/RECORD
