Metadata-Version: 2.4
Name: mcp-stargazing
Version: 0.1.7
Summary: An MCP server that provides real-time astronomical data, smart stargazing planning, and light pollution analysis for AI agents.
Author-email: Henry Gong <zhao.gong@outlook.com>
Project-URL: Homepage, https://github.com/StarGazer1995/mcp-stargazing
Project-URL: Issues, https://github.com/StarGazer1995/mcp-stargazing/issues
Classifier: Development Status :: 3 - Alpha
Classifier: Intended Audience :: Science/Research
Classifier: License :: OSI Approved :: MIT License
Classifier: Programming Language :: Python :: 3
Classifier: Topic :: Scientific/Engineering :: Astronomy
Requires-Python: >=3.13
License-File: LICENSE
Requires-Dist: fastmcp
Requires-Dist: astropy[all]
Requires-Dist: pytz
Requires-Dist: numpy
Requires-Dist: astroquery
Requires-Dist: rasterio
Requires-Dist: tzlocal
Requires-Dist: geopy
Requires-Dist: stargazing-place-finder>=0.3.1
Dynamic: license-file
